wtf/__init__.py
wtf/__main__.py
wtf/cli.py
wtf/ai/__init__.py
wtf/ai/client.py
wtf/ai/errors.py
wtf/ai/prompts.py
wtf/ai/tools.py
wtf/context/__init__.py
wtf/context/env.py
wtf/context/git.py
wtf/context/shell.py
wtf/conversation/__init__.py
wtf/conversation/history.py
wtf/conversation/memory.py
wtf/core/__init__.py
wtf/core/config.py
wtf/core/executor.py
wtf/core/permissions.py
wtf/setup/__init__.py
wtf/setup/collision.py
wtf/setup/hooks.py
wtf/utils/__init__.py
wtf/utils/security.py
wtf_ai-0.4.9.dist-info/licenses/LICENSE
wtf_ai-0.4.9.dist-info/METADATA
wtf_ai-0.4.9.dist-info/WHEEL
wtf_ai-0.4.9.dist-info/entry_points.txt
wtf_ai-0.4.9.dist-info/top_level.txt
wtf_ai-0.4.9.dist-info/RECORD
