Metadata-Version: 2.4
Name: wtf-ai
Version: 0.4.9
Summary: A command-line AI assistant that provides contextual help based on terminal history
Author: wtf-ai contributors
License-Expression: MIT
Project-URL: Homepage, https://github.com/davefowler/wtf-terminal-ai
Project-URL: Documentation, https://github.com/davefowler/wtf-terminal-ai
Project-URL: Repository, https://github.com/davefowler/wtf-terminal-ai
Project-URL: Issues, https://github.com/davefowler/wtf-terminal-ai/issues
Keywords: cli,ai,assistant,terminal,shell
Classifier: Development Status :: 3 - Alpha
Classifier: Intended Audience :: Developers
Classifier: Programming Language :: Python :: 3
Classifier: Programming Language :: Python :: 3.9
Classifier: Programming Language :: Python :: 3.10
Classifier: Programming Language :: Python :: 3.11
Classifier: Programming Language :: Python :: 3.12
Classifier: Programming Language :: Python :: 3.13
Classifier: Topic :: Software Development :: User Interfaces
Classifier: Topic :: System :: Shells
Requires-Python: >=3.9
License-File: LICENSE
Requires-Dist: anthropic>=0.18.0
Requires-Dist: openai>=1.12.0
Requires-Dist: google-generativeai>=0.3.0
Requires-Dist: llm>=0.13.0
Requires-Dist: llm-anthropic>=0.9.0
Requires-Dist: llm-gemini>=0.5.0
Requires-Dist: llm-ollama>=0.8.0
Requires-Dist: rich>=13.7.0
Requires-Dist: ddgs>=9.0.0
Provides-Extra: dev
Requires-Dist: pytest>=7.0.0; extra == "dev"
Requires-Dist: pytest-cov>=4.0.0; extra == "dev"
Requires-Dist: mkdocs>=1.5.0; extra == "dev"
Requires-Dist: mkdocs-material>=9.0.0; extra == "dev"
Dynamic: license-file
